{
  "OldId": 1685091170,
  "NewId": 1244737609,
  "Unk": [
    0
  ],
  "Modifications": [
    {
      "Id": 1953458293,
      "Type": 3,
      "Value": "TRIGSTR_293"
    },
    {
      "Id": 1835101813,
      "Type": 3,
      "Value": "TRIGSTR_4684"
    },
    {
      "Id": 1885959285,
      "Type": 3,
      "Value": ""
    },
    {
      "Id": 1651864693,
      "Type": 3,
      "Value": "TRIGSTR_3106"
    },
    {
      "Id": 1819240297,
      "Value": 0
    },
    {
      "Id": 1868786025,
      "Type": 3,
      "Value": "ReplaceableTextures\\CommandButtons\\BTNBarkskin.blp"
    },
    {
      "Id": 1768055145,
      "Type": 3,
      "Value": "A05X"
    },
    {
      "Id": 1818846825,
      "Type": 3,
      "Value": "war3mapImported\\SantaHat.mdl"
    },
    {
      "Id": 1936024681,
      "Type": 3,
      "Value": "TRIGSTR_3107"
    },
    {
      "Id": 1886545001,
      "Value": 1
    }
  ]
}