{
  "OldId": 1701668946,
  "NewId": 875573330,
  "Unk": [
    0
  ],
  "Modifications": [
    {
      "Level": 1,
      "Id": 1835101799,
      "Type": 3,
      "Value": "PU_Energy"
    },
    {
      "Id": 828794215,
      "Type": 3,
      "Value": "rmnx"
    },
    {
      "Id": 828465767,
      "Type": 2,
      "Value": 50
    },
    {
      "Id": 829386087,
      "Type": 2,
      "Value": 50
    },
    {
      "Id": 1819700327,
      "Value": 1
    },
    {
      "Id": 1936483175,
      "Type": 3,
      "Value": ""
    }
  ]
}