{
  "OldId": 1668697665,
  "NewId": 1127559233,
  "Unk": [
    0
  ],
  "Modifications": [
    {
      "Id": 1835101793,
      "Type": 3,
      "Value": "Fountain of Chaos"
    },
    {
      "Id": 2037082209,
      "Type": 3,
      "Value": "D"
    },
    {
      "Id": 1802007137,
      "Type": 3,
      "Value": "D"
    },
    {
      "Level": 1,
      "Id": 829453409,
      "Type": 3,
      "Value": "[D] Fountain of Chaos"
    },
    {
      "Id": 1953653089,
      "Type": 3,
      "Value": "ReplaceableTextures\\CommandButtons\\BTNWandOfShadowSight.blp"
    },
    {
      "Id": 2020631137,
      "Value": 2
    },
    {
      "Level": 1,
      "Id": 828536161,
      "Type": 3,
      "Value": "Causes webbing to erupt from the ground. When it lands, it will trap units it hits and damage them. This ability can damage friendlies!"
    },
    {
      "Id": 1768841569,
      "Type": 3,
      "Value": "spell"
    }
  ]
}