{
  "OldId": 1885621825,
  "NewId": 959524929,
  "Unk": [
    0
  ],
  "Modifications": [
    {
      "Id": 1835101793,
      "Type": 3,
      "Value": "Fusion Bomb"
    },
    {
      "Id": 2037082209,
      "Type": 3,
      "Value": "S"
    },
    {
      "Level": 1,
      "Id": 829453409,
      "Type": 3,
      "Value": "Fusion Bomb"
    },
    {
      "Id": 1952540001,
      "Type": 3,
      "Value": "Abilities\\Spells\\Human\\Defend\\DefendCaster.mdl"
    },
    {
      "Id": 1953653089,
      "Type": 3,
      "Value": "ReplaceableTextures\\CommandButtons\\BTNDrum.blp"
    }
  ]
}