[
  {
    "State": 2,
    "Life": 100,
    "TypeId": 1919112268,
    "Variation": 1,
    "Position": {
      "X": -10752,
      "Y": -768,
      "Z": -256
    },
    "Rotation": 1.7104226,
    "Scale": {
      "X": 1.0717857,
      "Y": 1.0717857,
      "Z": 1.0717857
    },
    "SkinId": 1919112268,
    "MapItemTableId": -1,
    "ItemTableSets": [],
    "CreationNumber": 1456
  },
  {
    "State": 2,
    "Life": 255,
    "TypeId": 825241668,
    "Position": {
      "X": -10784,
      "Y": -736,
      "Z": -224
    },
    "Rotation": 6.0388393,
    "Scale": {
      "X": 0.4,
      "Y": 0.4,
      "Z": 0.4
    },
    "SkinId": 825241668,
    "MapItemTableId": -1,
    "ItemTableSets": [],
    "CreationNumber": 1459
  },
  {
    "State": 6,
    "Life": 255,
    "TypeId": 1127231556,
    "Position": {
      "X": -10784,
      "Y": -608,
      "Z": -262.39996
    },
    "Scale": {
      "X": 1.5,
      "Y": 1.5,
      "Z": 1.5
    },
    "SkinId": 1127231556,
    "MapItemTableId": -1,
    "ItemTableSets": [],
    "CreationNumber": 1462
  },
  {
    "State": 2,
    "Life": 100,
    "TypeId": 1651528793,
    "Position": {
      "X": -10784,
      "Y": -672,
      "Z": -224
    },
    "Rotation": 4.712389,
    "Scale": {
      "X": 1,
      "Y": 1,
      "Z": 1
    },
    "SkinId": 1651528793,
    "MapItemTableId": -1,
    "ItemTableSets": [],
    "CreationNumber": 1460
  },
  {
    "State": 2,
    "Life": 100,
    "TypeId": 1651528793,
    "Position": {
      "X": -10784,
      "Y": -544,
      "Z": -224
    },
    "Rotation": 4.712389,
    "Scale": {
      "X": 1,
      "Y": 1,
      "Z": 1
    },
    "SkinId": 1651528793,
    "MapItemTableId": -1,
    "ItemTableSets": [],
    "CreationNumber": 1463
  }
]