[
  {
    "State": 2,
    "Life": 100,
    "TypeId": 2020430936,
    "Position": {
      "X": -2720,
      "Y": -1984,
      "Z": -256
    },
    "Scale": {
      "X": 0.85,
      "Y": 0.85,
      "Z": 0.85
    },
    "SkinId": 2020430936,
    "MapItemTableId": -1,
    "ItemTableSets": [],
    "CreationNumber": 1734
  },
  {
    "State": 2,
    "Life": 100,
    "TypeId": 2020430936,
    "Position": {
      "X": -2720,
      "Y": -1728,
      "Z": -256
    },
    "Scale": {
      "X": 0.85,
      "Y": 0.85,
      "Z": 0.85
    },
    "SkinId": 2020430936,
    "MapItemTableId": -1,
    "ItemTableSets": [],
    "CreationNumber": 1743
  },
  {
    "State": 2,
    "Life": 100,
    "TypeId": 1919046732,
    "Position": {
      "X": -3040,
      "Y": -2016,
      "Z": -256
    },
    "Rotation": 1.780236,
    "Scale": {
      "X": 0.95708483,
      "Y": 0.95708483,
      "Z": 0.95708483
    },
    "SkinId": 1919046732,
    "MapItemTableId": -1,
    "ItemTableSets": [],
    "CreationNumber": 1670
  },
  {
    "State": 2,
    "Life": 100,
    "TypeId": 1919046732,
    "Position": {
      "X": -3040,
      "Y": -1952,
      "Z": -256
    },
    "Rotation": 2.8797936,
    "Scale": {
      "X": 1.0340067,
      "Y": 1.0340067,
      "Z": 1.0340067
    },
    "SkinId": 1919046732,
    "MapItemTableId": -1,
    "ItemTableSets": [],
    "CreationNumber": 1671
  },
  {
    "State": 2,
    "Life": 100,
    "TypeId": 1919046732,
    "Position": {
      "X": -3040,
      "Y": -1888,
      "Z": -256
    },
    "Rotation": 3.5779252,
    "Scale": {
      "X": 0.96343267,
      "Y": 0.96343267,
      "Z": 0.96343267
    },
    "SkinId": 1919046732,
    "MapItemTableId": -1,
    "ItemTableSets": [],
    "CreationNumber": 1672
  },
  {
    "State": 2,
    "Life": 100,
    "TypeId": 1919046732,
    "Position": {
      "X": -3040,
      "Y": -1824,
      "Z": -256
    },
    "Rotation": 1.7278762,
    "Scale": {
      "X": 1.0129337,
      "Y": 1.0129337,
      "Z": 1.0129337
    },
    "SkinId": 1919046732,
    "MapItemTableId": -1,
    "ItemTableSets": [],
    "CreationNumber": 1673
  },
  {
    "State": 2,
    "Life": 100,
    "TypeId": 1919046732,
    "Position": {
      "X": -3040,
      "Y": -1760,
      "Z": -256
    },
    "Rotation": 0.43633235,
    "Scale": {
      "X": 0.96324956,
      "Y": 0.96324956,
      "Z": 0.96324956
    },
    "SkinId": 1919046732,
    "MapItemTableId": -1,
    "ItemTableSets": [],
    "CreationNumber": 1674
  },
  {
    "State": 2,
    "Life": 100,
    "TypeId": 1919046732,
    "Position": {
      "X": -3040,
      "Y": -1696,
      "Z": -256
    },
    "Rotation": 2.2340217,
    "Scale": {
      "X": 1.1166356,
      "Y": 1.1166356,
      "Z": 1.1166356
    },
    "SkinId": 1919046732,
    "MapItemTableId": -1,
    "ItemTableSets": [],
    "CreationNumber": 1675
  },
  {
    "State": 2,
    "Life": 100,
    "TypeId": 1919046732,
    "Position": {
      "X": -3040,
      "Y": -1632,
      "Z": -256
    },
    "Rotation": 2.2863815,
    "Scale": {
      "X": 0.9482803,
      "Y": 0.9482803,
      "Z": 0.9482803
    },
    "SkinId": 1919046732,
    "MapItemTableId": -1,
    "ItemTableSets": [],
    "CreationNumber": 1676
  },
  {
    "State": 2,
    "Life": 100,
    "TypeId": 1919046732,
    "Position": {
      "X": -3040,
      "Y": -1568,
      "Z": -256
    },
    "Rotation": 6.265733,
    "Scale": {
      "X": 1.2052461,
      "Y": 1.2052461,
      "Z": 1.2052461
    },
    "SkinId": 1919046732,
    "MapItemTableId": -1,
    "ItemTableSets": [],
    "CreationNumber": 1677
  },
  {
    "State": 2,
    "Life": 100,
    "TypeId": 1919046732,
    "Position": {
      "X": -2976,
      "Y": -2016,
      "Z": -256
    },
    "Rotation": 3.560472,
    "Scale": {
      "X": 1.2885005,
      "Y": 1.2885005,
      "Z": 1.2885005
    },
    "SkinId": 1919046732,
    "MapItemTableId": -1,
    "ItemTableSets": [],
    "CreationNumber": 1684
  },
  {
    "State": 2,
    "Life": 100,
    "TypeId": 1919046732,
    "Position": {
      "X": -2976,
      "Y": -1952,
      "Z": -256
    },
    "Rotation": 1.9547689,
    "Scale": {
      "X": 1.3837641,
      "Y": 1.3837641,
      "Z": 1.3837641
    },
    "SkinId": 1919046732,
    "MapItemTableId": -1,
    "ItemTableSets": [],
    "CreationNumber": 1685
  },
  {
    "State": 2,
    "Life": 100,
    "TypeId": 1919046732,
    "Position": {
      "X": -2976,
      "Y": -1888,
      "Z": -256
    },
    "Rotation": 1.4660767,
    "Scale": {
      "X": 0.92977077,
      "Y": 0.92977077,
      "Z": 0.92977077
    },
    "SkinId": 1919046732,
    "MapItemTableId": -1,
    "ItemTableSets": [],
    "CreationNumber": 1686
  },
  {
    "State": 2,
    "Life": 100,
    "TypeId": 1919046732,
    "Position": {
      "X": -2976,
      "Y": -1824,
      "Z": -256
    },
    "Rotation": 0.24434611,
    "Scale": {
      "X": 1.3330576,
      "Y": 1.3330576,
      "Z": 1.3330576
    },
    "SkinId": 1919046732,
    "MapItemTableId": -1,
    "ItemTableSets": [],
    "CreationNumber": 1687
  },
  {
    "State": 2,
    "Life": 100,
    "TypeId": 1919046732,
    "Position": {
      "X": -2976,
      "Y": -1760,
      "Z": -256
    },
    "Rotation": 2.5307276,
    "Scale": {
      "X": 1.2002716,
      "Y": 1.2002716,
      "Z": 1.2002716
    },
    "SkinId": 1919046732,
    "MapItemTableId": -1,
    "ItemTableSets": [],
    "CreationNumber": 1688
  },
  {
    "State": 2,
    "Life": 100,
    "TypeId": 1919046732,
    "Position": {
      "X": -2976,
      "Y": -1696,
      "Z": -256
    },
    "Rotation": 0.47123894,
    "Scale": {
      "X": 1.2491164,
      "Y": 1.2491164,
      "Z": 1.2491164
    },
    "SkinId": 1919046732,
    "MapItemTableId": -1,
    "ItemTableSets": [],
    "CreationNumber": 1689
  },
  {
    "State": 2,
    "Life": 100,
    "TypeId": 1919046732,
    "Position": {
      "X": -2976,
      "Y": -1632,
      "Z": -256
    },
    "Rotation": 1.0122911,
    "Scale": {
      "X": 1.3237189,
      "Y": 1.3237189,
      "Z": 1.3237189
    },
    "SkinId": 1919046732,
    "MapItemTableId": -1,
    "ItemTableSets": [],
    "CreationNumber": 1690
  },
  {
    "State": 2,
    "Life": 100,
    "TypeId": 1919046732,
    "Position": {
      "X": -2976,
      "Y": -1568,
      "Z": -256
    },
    "Rotation": 1.9547689,
    "Scale": {
      "X": 0.9058748,
      "Y": 0.9058748,
      "Z": 0.9058748
    },
    "SkinId": 1919046732,
    "MapItemTableId": -1,
    "ItemTableSets": [],
    "CreationNumber": 1691
  },
  {
    "State": 2,
    "Life": 100,
    "TypeId": 1919046732,
    "Position": {
      "X": -2912,
      "Y": -2016,
      "Z": -256
    },
    "Rotation": 2.321288,
    "Scale": {
      "X": 1.0853541,
      "Y": 1.0853541,
      "Z": 1.0853541
    },
    "SkinId": 1919046732,
    "MapItemTableId": -1,
    "ItemTableSets": [],
    "CreationNumber": 1696
  },
  {
    "State": 2,
    "Life": 100,
    "TypeId": 1919046732,
    "Position": {
      "X": -2912,
      "Y": -1952,
      "Z": -256
    },
    "Rotation": 4.974189,
    "Scale": {
      "X": 1.0237068,
      "Y": 1.0237068,
      "Z": 1.0237068
    },
    "SkinId": 1919046732,
    "MapItemTableId": -1,
    "ItemTableSets": [],
    "CreationNumber": 1697
  },
  {
    "State": 2,
    "Life": 100,
    "TypeId": 1919046732,
    "Position": {
      "X": -2912,
      "Y": -1888,
      "Z": -256
    },
    "Rotation": 1.5358899,
    "Scale": {
      "X": 1.3622333,
      "Y": 1.3622333,
      "Z": 1.3622333
    },
    "SkinId": 1919046732,
    "MapItemTableId": -1,
    "ItemTableSets": [],
    "CreationNumber": 1698
  },
  {
    "State": 2,
    "Life": 100,
    "TypeId": 1919046732,
    "Position": {
      "X": -2912,
      "Y": -1824,
      "Z": -256
    },
    "Rotation": 2.722714,
    "Scale": {
      "X": 0.9521714,
      "Y": 0.9521714,
      "Z": 0.9521714
    },
    "SkinId": 1919046732,
    "MapItemTableId": -1,
    "ItemTableSets": [],
    "CreationNumber": 1699
  },
  {
    "State": 2,
    "Life": 100,
    "TypeId": 1919046732,
    "Position": {
      "X": -2912,
      "Y": -1760,
      "Z": -256
    },
    "Rotation": 0.8726647,
    "Scale": {
      "X": 1.3825587,
      "Y": 1.3825587,
      "Z": 1.3825587
    },
    "SkinId": 1919046732,
    "MapItemTableId": -1,
    "ItemTableSets": [],
    "CreationNumber": 1700
  },
  {
    "State": 2,
    "Life": 100,
    "TypeId": 1919046732,
    "Position": {
      "X": -2912,
      "Y": -1696,
      "Z": -256
    },
    "Rotation": 5.1487217,
    "Scale": {
      "X": 1.130079,
      "Y": 1.130079,
      "Z": 1.130079
    },
    "SkinId": 1919046732,
    "MapItemTableId": -1,
    "ItemTableSets": [],
    "CreationNumber": 1701
  },
  {
    "State": 2,
    "Life": 100,
    "TypeId": 1919046732,
    "Position": {
      "X": -2912,
      "Y": -1632,
      "Z": -256
    },
    "Rotation": 1.5707965,
    "Scale": {
      "X": 1.2535264,
      "Y": 1.2535264,
      "Z": 1.2535264
    },
    "SkinId": 1919046732,
    "MapItemTableId": -1,
    "ItemTableSets": [],
    "CreationNumber": 1702
  },
  {
    "State": 2,
    "Life": 100,
    "TypeId": 1919046732,
    "Position": {
      "X": -2912,
      "Y": -1568,
      "Z": -256
    },
    "Rotation": 3.4732056,
    "Scale": {
      "X": 0.9056917,
      "Y": 0.9056917,
      "Z": 0.9056917
    },
    "SkinId": 1919046732,
    "MapItemTableId": -1,
    "ItemTableSets": [],
    "CreationNumber": 1703
  },
  {
    "State": 2,
    "Life": 100,
    "TypeId": 1919046732,
    "Position": {
      "X": -2848,
      "Y": -2016,
      "Z": -256
    },
    "Rotation": 2.3387415,
    "Scale": {
      "X": 1.2774072,
      "Y": 1.2774072,
      "Z": 1.2774072
    },
    "SkinId": 1919046732,
    "MapItemTableId": -1,
    "ItemTableSets": [],
    "CreationNumber": 1707
  },
  {
    "State": 2,
    "Life": 100,
    "TypeId": 1919046732,
    "Position": {
      "X": -2848,
      "Y": -1952,
      "Z": -256
    },
    "Rotation": 4.031711,
    "Scale": {
      "X": 0.9620899,
      "Y": 0.9620899,
      "Z": 0.9620899
    },
    "SkinId": 1919046732,
    "MapItemTableId": -1,
    "ItemTableSets": [],
    "CreationNumber": 1708
  },
  {
    "State": 2,
    "Life": 100,
    "TypeId": 1919046732,
    "Position": {
      "X": -2848,
      "Y": -1888,
      "Z": -256
    },
    "Rotation": 5.393068,
    "Scale": {
      "X": 1.1900936,
      "Y": 1.1900936,
      "Z": 1.1900936
    },
    "SkinId": 1919046732,
    "MapItemTableId": -1,
    "ItemTableSets": [],
    "CreationNumber": 1709
  },
  {
    "State": 2,
    "Life": 100,
    "TypeId": 1919046732,
    "Position": {
      "X": -2848,
      "Y": -1824,
      "Z": -256
    },
    "Rotation": 2.076942,
    "Scale": {
      "X": 1.3511245,
      "Y": 1.3511245,
      "Z": 1.3511245
    },
    "SkinId": 1919046732,
    "MapItemTableId": -1,
    "ItemTableSets": [],
    "CreationNumber": 1710
  },
  {
    "State": 2,
    "Life": 100,
    "TypeId": 1919046732,
    "Position": {
      "X": -2848,
      "Y": -1760,
      "Z": -256
    },
    "Rotation": 0.6981318,
    "Scale": {
      "X": 1.2845637,
      "Y": 1.2845637,
      "Z": 1.2845637
    },
    "SkinId": 1919046732,
    "MapItemTableId": -1,
    "ItemTableSets": [],
    "CreationNumber": 1711
  },
  {
    "State": 2,
    "Life": 100,
    "TypeId": 1919046732,
    "Position": {
      "X": -2848,
      "Y": -1696,
      "Z": -256
    },
    "Rotation": 4.4854965,
    "Scale": {
      "X": 0.9845515,
      "Y": 0.9845515,
      "Z": 0.9845515
    },
    "SkinId": 1919046732,
    "MapItemTableId": -1,
    "ItemTableSets": [],
    "CreationNumber": 1712
  },
  {
    "State": 2,
    "Life": 100,
    "TypeId": 1919046732,
    "Position": {
      "X": -2848,
      "Y": -1632,
      "Z": -256
    },
    "Rotation": 0.20943953,
    "Scale": {
      "X": 1.2661306,
      "Y": 1.2661306,
      "Z": 1.2661306
    },
    "SkinId": 1919046732,
    "MapItemTableId": -1,
    "ItemTableSets": [],
    "CreationNumber": 1713
  },
  {
    "State": 2,
    "Life": 100,
    "TypeId": 1919046732,
    "Position": {
      "X": -2848,
      "Y": -1568,
      "Z": -256
    },
    "Rotation": 5.5326943,
    "Scale": {
      "X": 1.3925534,
      "Y": 1.3925534,
      "Z": 1.3925534
    },
    "SkinId": 1919046732,
    "MapItemTableId": -1,
    "ItemTableSets": [],
    "CreationNumber": 1714
  },
  {
    "State": 2,
    "Life": 100,
    "TypeId": 1919046732,
    "Position": {
      "X": -2784,
      "Y": -2016,
      "Z": -256
    },
    "Rotation": 3.7699115,
    "Scale": {
      "X": 1.0551561,
      "Y": 1.0551561,
      "Z": 1.0551561
    },
    "SkinId": 1919046732,
    "MapItemTableId": -1,
    "ItemTableSets": [],
    "CreationNumber": 1716
  },
  {
    "State": 2,
    "Life": 100,
    "TypeId": 1919046732,
    "Position": {
      "X": -2784,
      "Y": -1952,
      "Z": -256
    },
    "Rotation": 0.087266475,
    "Scale": {
      "X": 1.013483,
      "Y": 1.013483,
      "Z": 1.013483
    },
    "SkinId": 1919046732,
    "MapItemTableId": -1,
    "ItemTableSets": [],
    "CreationNumber": 1717
  },
  {
    "State": 2,
    "Life": 100,
    "TypeId": 1919046732,
    "Position": {
      "X": -2784,
      "Y": -1888,
      "Z": -256
    },
    "Rotation": 2.0245821,
    "Scale": {
      "X": 1.171508,
      "Y": 1.171508,
      "Z": 1.171508
    },
    "SkinId": 1919046732,
    "MapItemTableId": -1,
    "ItemTableSets": [],
    "CreationNumber": 1718
  },
  {
    "State": 2,
    "Life": 100,
    "TypeId": 1919046732,
    "Position": {
      "X": -2784,
      "Y": -1824,
      "Z": -256
    },
    "Rotation": 5.0789084,
    "Scale": {
      "X": 1.2008972,
      "Y": 1.2008972,
      "Z": 1.2008972
    },
    "SkinId": 1919046732,
    "MapItemTableId": -1,
    "ItemTableSets": [],
    "CreationNumber": 1719
  },
  {
    "State": 2,
    "Life": 100,
    "TypeId": 1919046732,
    "Position": {
      "X": -2784,
      "Y": -1760,
      "Z": -256
    },
    "Rotation": 4.2760572,
    "Scale": {
      "X": 1.3301278,
      "Y": 1.3301278,
      "Z": 1.3301278
    },
    "SkinId": 1919046732,
    "MapItemTableId": -1,
    "ItemTableSets": [],
    "CreationNumber": 1720
  },
  {
    "State": 2,
    "Life": 100,
    "TypeId": 1919046732,
    "Position": {
      "X": -2784,
      "Y": -1696,
      "Z": -256
    },
    "Rotation": 1.6580629,
    "Scale": {
      "X": 1.3821161,
      "Y": 1.3821161,
      "Z": 1.3821161
    },
    "SkinId": 1919046732,
    "MapItemTableId": -1,
    "ItemTableSets": [],
    "CreationNumber": 1721
  },
  {
    "State": 2,
    "Life": 100,
    "TypeId": 1919046732,
    "Position": {
      "X": -2784,
      "Y": -1632,
      "Z": -256
    },
    "Rotation": 1.7104229,
    "Scale": {
      "X": 1.2473464,
      "Y": 1.2473464,
      "Z": 1.2473464
    },
    "SkinId": 1919046732,
    "MapItemTableId": -1,
    "ItemTableSets": [],
    "CreationNumber": 1722
  }
]