{
  "OldId": 1819044215,
  "NewId": 1429221449,
  "Unk": [
    0
  ],
  "Modifications": [
    {
      "Id": 1835101813,
      "Type": 3,
      "Value": "Tracking Device"
    },
    {
      "Id": 1936024681,
      "Type": 3,
      "Value": "Tracking Device"
    },
    {
      "Id": 1885959285,
      "Type": 3,
      "Value": "|cff800080Tracking Device|r"
    },
    {
      "Id": 1651864693,
      "Type": 3,
      "Value": "|cff80FF00Item-Type:|r Tracking/No Target|n|cff80FF00Charges:|r N/A|n|cff80FF00Cooldown:|r 45s|n|cff80FF00Description:|r A powerful locating device that can help you track players. Using it will ping the locations of nearby units within 8000 range and on the same station you are on."
    },
    {
      "Id": 1868786025,
      "Type": 3,
      "Value": "ReplaceableTextures\\CommandButtons\\BTNOrbPain.blp"
    },
    {
      "Id": 1818846825,
      "Type": 3,
      "Value": "Abilities\\Weapons\\NecromancerMissile\\NecromancerMissile.mdl"
    },
    {
      "Id": 1633907561,
      "Type": 1,
      "Value": 0.4
    }
  ]
}